redis_cache/__init__.py
python_redis_cache-4.0.0.dist-info/LICENSE
python_redis_cache-4.0.0.dist-info/METADATA
python_redis_cache-4.0.0.dist-info/WHEEL
python_redis_cache-4.0.0.dist-info/top_level.txt
python_redis_cache-4.0.0.dist-info/RECORD
