Metadata-Version: 2.1
Name: python-redis-cache
Version: 4.0.0
Summary: Basic Redis caching for functions
Home-page: http://github.com/taylorhakes/python-redis-cache
Author: Taylor Hakes
License: MIT
Requires-Python: >=3.8
License-File: LICENSE
Requires-Dist: redis
